pyneva/__init__.py
pyneva/__main__.py
pyneva/core.py
pyneva/meters.py
pyneva/tools.py
pyneva/types.py
pyneva-0.7.51.dist-info/LICENSE
pyneva-0.7.51.dist-info/METADATA
pyneva-0.7.51.dist-info/WHEEL
pyneva-0.7.51.dist-info/top_level.txt
pyneva-0.7.51.dist-info/RECORD
