Metadata-Version: 2.1
Name: pyneva
Version: 0.7.51
Summary: Custom library for electricity meters Neva MT
Home-page: https://github.com/vazelegend/pyneva
Author: Nikita Nemirovsky
Author-email: vaze.legend@gmail.com
License: MIT
Platform: any
Requires-Python: >=3.9
License-File: LICENSE
Requires-Dist: pyserial (>=3.5)
